{
	"took":133,
	"total":1911850,
	"size":10,
	"hits":[
		{
			"@timestamp":"2018-09-10T10:18:26.826Z",
			"beat":{
				"hostname":"xbrain-1",
				"name":"xbrain-1",
				"version":"5.4.0"
			},
			"metricset":{
				"module":"system",
				"name":"process",
				"rtt":4587
			},
			"system":{
				"process":{
					"cgroup":{
						"blkio":{
							"id":"fd6330ba3207d365e66643e90ee576f323065c8ba8220a4542c94671aacdffa6",
							"path":"/docker/fd6330ba3207d365e66643e90ee576f323065c8ba8220a4542c94671aacdffa6",
							"total":{
								"bytes":0,
								"ios":0
							}
						},
						"cpu":{
							"cfs":{
								"period":{
									"us":0
								},
								"quota":{
									"us":0
								},
								"shares":0
							},
							"id":"fd6330ba3207d365e66643e90ee576f323065c8ba8220a4542c94671aacdffa6",
							"path":"/docker/fd6330ba3207d365e66643e90ee576f323065c8ba8220a4542c94671aacdffa6",
							"rt":{
								"period":{
									"us":0
								},
								"runtime":{
									"us":0
								}
							},
							"stats":{
								"periods":0,
								"throttled":{
									"ns":0,
									"periods":0
								}
							}
						},
						"cpuacct":{
							"id":"fd6330ba3207d365e66643e90ee576f323065c8ba8220a4542c94671aacdffa6",
							"path":"/docker/fd6330ba3207d365e66643e90ee576f323065c8ba8220a4542c94671aacdffa6",
							"percpu":{},
							"stats":{
								"system":{
									"ns":0
								},
								"user":{
									"ns":0
								}
							},
							"total":{
								"ns":0
							}
						},
						"id":"fd6330ba3207d365e66643e90ee576f323065c8ba8220a4542c94671aacdffa6",
						"memory":{
							"id":"fd6330ba3207d365e66643e90ee576f323065c8ba8220a4542c94671aacdffa6",
							"kmem":{
								"failures":0,
								"limit":{
									"bytes":0
								},
								"usage":{
									"bytes":0,
									"max":{
										"bytes":0
									}
								}
							},
							"kmem_tcp":{
								"failures":0,
								"limit":{
									"bytes":0
								},
								"usage":{
									"bytes":0,
									"max":{
										"bytes":0
									}
								}
							},
							"mem":{
								"failures":0,
								"limit":{
									"bytes":0
								},
								"usage":{
									"bytes":0,
									"max":{
										"bytes":0
									}
								}
							},
							"memsw":{
								"failures":0,
								"limit":{
									"bytes":0
								},
								"usage":{
									"bytes":0,
									"max":{
										"bytes":0
									}
								}
							},
							"path":"/docker/fd6330ba3207d365e66643e90ee576f323065c8ba8220a4542c94671aacdffa6",
							"stats":{
								"active_anon":{
									"bytes":0
								},
								"active_file":{
									"bytes":0
								},
								"cache":{
									"bytes":0
								},
								"hierarchical_memory_limit":{
									"bytes":0
								},
								"hierarchical_memsw_limit":{
									"bytes":0
								},
								"inactive_anon":{
									"bytes":0
								},
								"inactive_file":{
									"bytes":0
								},
								"major_page_faults":0,
								"mapped_file":{
									"bytes":0
								},
								"page_faults":0,
								"pages_in":0,
								"pages_out":0,
								"rss":{
									"bytes":0
								},
								"rss_huge":{
									"bytes":0
								},
								"swap":{
									"bytes":0
								},
								"unevictable":{
									"bytes":0
								}
							}
						},
						"path":"/docker/fd6330ba3207d365e66643e90ee576f323065c8ba8220a4542c94671aacdffa6"
					},
					"cmdline":"ash /metricbeat/start.sh",
					"cpu":{
						"start_time":"2018-09-10T10:11:55.000Z",
						"total":{
							"pct":0.0
						}
					},
					"fd":{
						"limit":{
							"hard":65536,
							"soft":65536
						},
						"open":4
					},
					"memory":{
						"rss":{
							"bytes":507904,
							"pct":1.0E-4
						},
						"share":389120,
						"size":1609728
					},
					"name":"ash",
					"pgid":1,
					"pid":1,
					"ppid":0,
					"state":"sleeping",
					"username":"root"
				}
			},
			"type":"metricsets"
		},
		{
			"@timestamp":"2018-09-10T10:18:26.826Z",
			"beat":{
				"hostname":"xbrain-1",
				"name":"xbrain-1",
				"version":"5.4.0"
			},
			"metricset":{
				"module":"system",
				"name":"process",
				"rtt":4587
			},
			"system":{
				"process":{
					"cgroup":{
						"blkio":{
							"id":"fd6330ba3207d365e66643e90ee576f323065c8ba8220a4542c94671aacdffa6",
							"path":"/docker/fd6330ba3207d365e66643e90ee576f323065c8ba8220a4542c94671aacdffa6",
							"total":{
								"bytes":0,
								"ios":0
							}
						},
						"cpu":{
							"cfs":{
								"period":{
									"us":0
								},
								"quota":{
									"us":0
								},
								"shares":0
							},
							"id":"fd6330ba3207d365e66643e90ee576f323065c8ba8220a4542c94671aacdffa6",
							"path":"/docker/fd6330ba3207d365e66643e90ee576f323065c8ba8220a4542c94671aacdffa6",
							"rt":{
								"period":{
									"us":0
								},
								"runtime":{
									"us":0
								}
							},
							"stats":{
								"periods":0,
								"throttled":{
									"ns":0,
									"periods":0
								}
							}
						},
						"cpuacct":{
							"id":"fd6330ba3207d365e66643e90ee576f323065c8ba8220a4542c94671aacdffa6",
							"path":"/docker/fd6330ba3207d365e66643e90ee576f323065c8ba8220a4542c94671aacdffa6",
							"percpu":{},
							"stats":{
								"system":{
									"ns":0
								},
								"user":{
									"ns":0
								}
							},
							"total":{
								"ns":0
							}
						},
						"id":"fd6330ba3207d365e66643e90ee576f323065c8ba8220a4542c94671aacdffa6",
						"memory":{
							"id":"fd6330ba3207d365e66643e90ee576f323065c8ba8220a4542c94671aacdffa6",
							"kmem":{
								"failures":0,
								"limit":{
									"bytes":0
								},
								"usage":{
									"bytes":0,
									"max":{
										"bytes":0
									}
								}
							},
							"kmem_tcp":{
								"failures":0,
								"limit":{
									"bytes":0
								},
								"usage":{
									"bytes":0,
									"max":{
										"bytes":0
									}
								}
							},
							"mem":{
								"failures":0,
								"limit":{
									"bytes":0
								},
								"usage":{
									"bytes":0,
									"max":{
										"bytes":0
									}
								}
							},
							"memsw":{
								"failures":0,
								"limit":{
									"bytes":0
								},
								"usage":{
									"bytes":0,
									"max":{
										"bytes":0
									}
								}
							},
							"path":"/docker/fd6330ba3207d365e66643e90ee576f323065c8ba8220a4542c94671aacdffa6",
							"stats":{
								"active_anon":{
									"bytes":0
								},
								"active_file":{
									"bytes":0
								},
								"cache":{
									"bytes":0
								},
								"hierarchical_memory_limit":{
									"bytes":0
								},
								"hierarchical_memsw_limit":{
									"bytes":0
								},
								"inactive_anon":{
									"bytes":0
								},
								"inactive_file":{
									"bytes":0
								},
								"major_page_faults":0,
								"mapped_file":{
									"bytes":0
								},
								"page_faults":0,
								"pages_in":0,
								"pages_out":0,
								"rss":{
									"bytes":0
								},
								"rss_huge":{
									"bytes":0
								},
								"swap":{
									"bytes":0
								},
								"unevictable":{
									"bytes":0
								}
							}
						},
						"path":"/docker/fd6330ba3207d365e66643e90ee576f323065c8ba8220a4542c94671aacdffa6"
					},
					"cmdline":"metricbeat -e -v -c /metricbeat/metricbeat.yml",
					"cpu":{
						"start_time":"2018-09-10T10:11:55.000Z",
						"total":{
							"pct":0.004
						}
					},
					"fd":{
						"limit":{
							"hard":65536,
							"soft":65536
						},
						"open":6
					},
					"memory":{
						"rss":{
							"bytes":18329600,
							"pct":0.0022
						},
						"share":6897664,
						"size":710967296
					},
					"name":"metricbeat",
					"pgid":1,
					"pid":12,
					"ppid":1,
					"state":"sleeping",
					"username":"root"
				}
			},
			"type":"metricsets"
		},
		{
			"@timestamp":"2018-09-10T10:18:26.822Z",
			"beat":{
				"hostname":"xbrain-1",
				"name":"xbrain-1",
				"version":"5.4.0"
			},
			"metricset":{
				"module":"system",
				"name":"filesystem",
				"rtt":1764
			},
			"system":{
				"filesystem":{
					"available":0,
					"device_name":"sysfs",
					"files":0,
					"free":0,
					"free_files":0,
					"mount_point":"/sys",
					"total":0,
					"used":{
						"bytes":0,
						"pct":0.0
					}
				}
			},
			"type":"metricsets"
		},
		{
			"@timestamp":"2018-09-10T10:18:26.822Z",
			"beat":{
				"hostname":"xbrain-1",
				"name":"xbrain-1",
				"version":"5.4.0"
			},
			"metricset":{
				"module":"system",
				"name":"filesystem",
				"rtt":1764
			},
			"system":{
				"filesystem":{
					"available":0,
					"device_name":"cgroup",
					"files":0,
					"free":0,
					"free_files":0,
					"mount_point":"/sys/fs/cgroup/freezer",
					"total":0,
					"used":{
						"bytes":0,
						"pct":0.0
					}
				}
			},
			"type":"metricsets"
		},
		{
			"@timestamp":"2018-09-10T10:18:26.822Z",
			"beat":{
				"hostname":"xbrain-1",
				"name":"xbrain-1",
				"version":"5.4.0"
			},
			"metricset":{
				"module":"system",
				"name":"filesystem",
				"rtt":1764
			},
			"system":{
				"filesystem":{
					"available":0,
					"device_name":"cgroup",
					"files":0,
					"free":0,
					"free_files":0,
					"mount_point":"/sys/fs/cgroup/cpu,cpuacct",
					"total":0,
					"used":{
						"bytes":0,
						"pct":0.0
					}
				}
			},
			"type":"metricsets"
		},
		{
			"@timestamp":"2018-09-10T10:18:26.822Z",
			"beat":{
				"hostname":"xbrain-1",
				"name":"xbrain-1",
				"version":"5.4.0"
			},
			"metricset":{
				"module":"system",
				"name":"filesystem",
				"rtt":1764
			},
			"system":{
				"filesystem":{
					"available":97268781056,
					"device_name":"/dev/mapper/centos-root",
					"files":50851840,
					"free":97268781056,
					"free_files":50701048,
					"mount_point":"/etc/hosts",
					"total":104134082560,
					"used":{
						"bytes":6865301504,
						"pct":0.0659
					}
				}
			},
			"type":"metricsets"
		},
		{
			"@timestamp":"2018-09-10T10:18:26.822Z",
			"beat":{
				"hostname":"xbrain-1",
				"name":"xbrain-1",
				"version":"5.4.0"
			},
			"metricset":{
				"module":"system",
				"name":"filesystem",
				"rtt":1764
			},
			"system":{
				"filesystem":{
					"available":0,
					"device_name":"proc",
					"files":0,
					"free":0,
					"free_files":0,
					"mount_point":"/proc/bus",
					"total":0,
					"used":{
						"bytes":0,
						"pct":0.0
					}
				}
			},
			"type":"metricsets"
		},
		{
			"@timestamp":"2018-09-10T10:18:26.822Z",
			"beat":{
				"hostname":"xbrain-1",
				"name":"xbrain-1",
				"version":"5.4.0"
			},
			"metricset":{
				"module":"system",
				"name":"filesystem",
				"rtt":1764
			},
			"system":{
				"filesystem":{
					"available":0,
					"device_name":"proc",
					"files":0,
					"free":0,
					"free_files":0,
					"mount_point":"/proc/fs",
					"total":0,
					"used":{
						"bytes":0,
						"pct":0.0
					}
				}
			},
			"type":"metricsets"
		},
		{
			"@timestamp":"2018-09-10T10:18:26.822Z",
			"beat":{
				"hostname":"xbrain-1",
				"name":"xbrain-1",
				"version":"5.4.0"
			},
			"metricset":{
				"module":"system",
				"name":"filesystem",
				"rtt":1764
			},
			"system":{
				"filesystem":{
					"available":67108864,
					"device_name":"tmpfs",
					"files":1001179,
					"free":67108864,
					"free_files":1001163,
					"mount_point":"/proc/keys",
					"total":67108864,
					"used":{
						"bytes":0,
						"pct":0.0
					}
				}
			},
			"type":"metricsets"
		},
		{
			"@timestamp":"2018-09-10T10:18:26.822Z",
			"beat":{
				"hostname":"xbrain-1",
				"name":"xbrain-1",
				"version":"5.4.0"
			},
			"metricset":{
				"module":"system",
				"name":"filesystem",
				"rtt":1764
			},
			"system":{
				"filesystem":{
					"available":10630909952,
					"device_name":"rootfs",
					"files":10485760,
					"free":10630909952,
					"free_files":10482833,
					"mount_point":"/",
					"total":10726932480,
					"used":{
						"bytes":96022528,
						"pct":0.009
					}
				}
			},
			"type":"metricsets"
		}
	]
}